[
	{
		"Na0": "punch (left jab)",
		"Na1": "punch (quick left jab)",
		"Na2": "Na0.punch",
		"Na3": ""
	},
	{
		"Na0": "",
		"Na1": "",
		"Na2": "kick (high left kick)",
		"Na3": "Na0.all"
	},
	{
		"Na0": "",
		"Na1": "",
		"Na2": "heavy (quick version of wind-up punch)",
		"Na3": "Na0.all"
	},
	{
		"Na0": "",
		"Na1": "",
		"Na2": "Na0.jump",
		"Na3": ""
	},
	{
		"Na0": "",
		"Na1": "Na0.kick",
		"Na2": "",
		"Na3": ""
	},
	{
		"Na0": "",
		"Na1": "heavy (1-2 combo)",
		"Na2": "Na0.punch",
		"Na3": ""
	},
	{
		"Na0": "",
		"Na1": "",
		"Na2": "Na0.kick",
		"Na3": ""
	},
	{
		"Na0": "",
		"Na1": "",
		"Na2": "heavy (right back-hand slap)",
		"Na3": "Na0.all"
	},
	{
		"Na0": "",
		"Na1": "",
		"Na2": "Na0.jump [+ follow_up_power_up]",
		"Na3": ""
	},
	{
		"Na0": "",
		"Na1": "Na0.jump",
		"Na2": "",
		"Na3": ""
	},
	{
		"Na0": "kick (low right kick)",
		"Na1": "Na0.punch",
		"Na2": "",
		"Na3": ""
	},
	{
		"Na0": "",
		"Na1": "kick (quick mid right kick)",
		"Na2": "Na0.punch",
		"Na3": ""
	},
	{
		"Na0": "",
		"Na1": "",
		"Na2": "kick (low left kick)",
		"Na3": "Na0.all"
	},
	{
		"Na0": "",
		"Na1": "",
		"Na2": "{heavy invalidated}",
		"Na3": "Na0.all"
	},
	{
		"Na0": "",
		"Na1": "",
		"Na2": "jump (resets character orientation mid air)",
		"Na3": "all = Na0.kick.Na1.jump.Na2.all"
	},
	{
		"Na0": "",
		"Na1": "heavy (after stepping back to NA0 position, mid left kick that also leaps the character forward by a bit)",
		"Na2": "Na0.all",
		"Na3": ""
	},
	{
		"Na0": "",
		"Na1": "jump (resets character orientation mid air)",
		"Na2": "{punch invalidated}",
		"Na3": "Na0.all"
	},
	{
		"Na0": "",
		"Na1": "",
		"Na2": "kick (mid-air left mid swing kick)",
		"Na3": "Na0.all"
	},
	{
		"Na0": "",
		"Na1": "",
		"Na2": "{heavy invalidated}",
		"Na3": "Na0.all"
	},
	{
		"Na0": "",
		"Na1": "",
		"Na2": "{jump invalidated}",
		"Na3": "Na0.all"
	},
	{
		"Na0": "heavy (wind-up punch)",
		"Na1": "{inputs invalidated}",
		"Na2": "NaO.all",
		"Na3": ""
	},
	{
		"Na0": "jump (jump straight up)",
		"Na1": "{punch invalidated}",
		"Na2": "Na0.all",
		"Na3": ""
	},
	{
		"Na0": "",
		"Na1": "kick (air kick)",
		"Na2": "Na0.punch",
		"Na3": ""
	},
	{
		"Na0": "",
		"Na1": "",
		"Na2": "kick (kick-push enemy back and jump back and create distance)",
		"Na3": "Na0.all [+ power_up]"
	},
	{
		"Na0": "",
		"Na1": "",
		"Na2": "Na0.heavy",
		"Na3": ""
	},
	{
		"Na0": "",
		"Na1": "",
		"Na2": "Na0.jump",
		"Na3": ""
	},
	{
		"Na0": "",
		"Na1": "heavy (superman punch)",
		"Na2": "Na0.all",
		"Na3": ""
	},
	{
		"Na0": "",
		"Na1": "jump (double jump if elevated surface nearby) or else Na0.jump",
		"Na2": "{punch invalidated}",
		"Na3": "Na0.all"
	},
	{
		"Na0": "",
		"Na1": "",
		"Na2": "kick (knees to the face)",
		"Na3": "{punch invalidated} > Na0.all"
	},
	{
		"Na0": "",
		"Na1": "",
		"Na2": "",
		"Na3": "kick = Na0.jump.Na1.kick.Na2.kick"
	},
	{
		"Na0": "",
		"Na1": "",
		"Na2": "",
		"Na3": "heavy = Na0.kick.Na1.jump.Na2.kick"
	},
	{
		"Na0": "",
		"Na1": "",
		"Na2": "",
		"Na3": "{jump invalidated} > Na0.all"
	},
	{
		"Na0": "",
		"Na1": "",
		"Na2": "heavy (elbows on top of the head)",
		"Na3": "{punch ivalidated} > Na0.all"
	},
	{
		"Na0": "",
		"Na1": "",
		"Na2": "",
		"Na3": "kick = Na0.jump.Na1.jump.Na2.kick"
	},
	{
		"Na0": "",
		"Na1": "",
		"Na2": "",
		"Na3": "heavy = Na0.jump.Na1.jump.Na2.kick"
	},
	{
		"Na0": "",
		"Na1": "",
		"Na2": "",
		"Na3": "{jump invalidated} > Na0.all"
	},
	{
		"Na0": "",
		"Na1": "",
		"Na2": "jump (steps on the enemy to jump behind them)",
		"Na3": "Na0.all"
	}
]
